Opencv3HeQt5JisuanjiShijueChuyi/README.md
Opencv3HeQt5JisuanjiShijueChuyi/__init__.py
Opencv3HeQt5JisuanjiShijueChuyi/__main__.py
Opencv3HeQt5JisuanjiShijueChuyi/file.epub
Opencv3HeQt5JisuanjiShijueChuyi/index.html
Opencv3HeQt5JisuanjiShijueChuyi/css/__init__.py
Opencv3HeQt5JisuanjiShijueChuyi/css/annotations.css
Opencv3HeQt5JisuanjiShijueChuyi/css/main.css
Opencv3HeQt5JisuanjiShijueChuyi/css/normalize.css
Opencv3HeQt5JisuanjiShijueChuyi/css/popup.css
Opencv3HeQt5JisuanjiShijueChuyi/font/__init__.py
Opencv3HeQt5JisuanjiShijueChuyi/font/fontello.eot
Opencv3HeQt5JisuanjiShijueChuyi/font/fontello.svg
Opencv3HeQt5JisuanjiShijueChuyi/font/fontello.ttf
Opencv3HeQt5JisuanjiShijueChuyi/font/fontello.woff
Opencv3HeQt5JisuanjiShijueChuyi/img/__init__.py
Opencv3HeQt5JisuanjiShijueChuyi/img/annotator-glyph-sprite.png
Opencv3HeQt5JisuanjiShijueChuyi/img/annotator-icon-sprite.png
Opencv3HeQt5JisuanjiShijueChuyi/img/apple-touch-icon.png
Opencv3HeQt5JisuanjiShijueChuyi/img/cancelfullscreen.png
Opencv3HeQt5JisuanjiShijueChuyi/img/close.png
Opencv3HeQt5JisuanjiShijueChuyi/img/fullscreen.png
Opencv3HeQt5JisuanjiShijueChuyi/img/loader.gif
Opencv3HeQt5JisuanjiShijueChuyi/img/menu-icon.png
Opencv3HeQt5JisuanjiShijueChuyi/img/save.png
Opencv3HeQt5JisuanjiShijueChuyi/img/saved.png
Opencv3HeQt5JisuanjiShijueChuyi/img/settings-s.png
Opencv3HeQt5JisuanjiShijueChuyi/img/settings.png
Opencv3HeQt5JisuanjiShijueChuyi/img/star.png
Opencv3HeQt5JisuanjiShijueChuyi/js/__init__.py
Opencv3HeQt5JisuanjiShijueChuyi/js/epub.js
Opencv3HeQt5JisuanjiShijueChuyi/js/epub.min.js
Opencv3HeQt5JisuanjiShijueChuyi/js/epub.min.map
Opencv3HeQt5JisuanjiShijueChuyi/js/hooks.min.js
Opencv3HeQt5JisuanjiShijueChuyi/js/hooks.min.map
Opencv3HeQt5JisuanjiShijueChuyi/js/reader.js
Opencv3HeQt5JisuanjiShijueChuyi/js/reader.js.map
Opencv3HeQt5JisuanjiShijueChuyi/js/reader.min.js
Opencv3HeQt5JisuanjiShijueChuyi/js/reader.min.map
Opencv3HeQt5JisuanjiShijueChuyi/js/hooks/__init__.py
opencv3_he_qt5_jisuanji_shijue_chuyi-2024.3.6.0.dist-info/METADATA
opencv3_he_qt5_jisuanji_shijue_chuyi-2024.3.6.0.dist-info/WHEEL
opencv3_he_qt5_jisuanji_shijue_chuyi-2024.3.6.0.dist-info/entry_points.txt
opencv3_he_qt5_jisuanji_shijue_chuyi-2024.3.6.0.dist-info/top_level.txt
opencv3_he_qt5_jisuanji_shijue_chuyi-2024.3.6.0.dist-info/RECORD
